redis_queue.py
setup.py
redis_queue_pyclj.egg-info/PKG-INFO
redis_queue_pyclj.egg-info/SOURCES.txt
redis_queue_pyclj.egg-info/dependency_links.txt
redis_queue_pyclj.egg-info/not-zip-safe
redis_queue_pyclj.egg-info/requires.txt
redis_queue_pyclj.egg-info/top_level.txt