Metadata-Version: 1.0
Name: redis-queue-pyclj
Version: 0.1.0
Summary: Some fault tolerance over Redis lists
Home-page: https://github.com/boechat107/redis-queue
Author: Andre A. Boechat
Author-email: boechat107@gmail.com
License: Eclipse
Platform: UNKNOWN
